tsf/__init__.py
tsf/__main__.py
tsf/config.ini
tsf/constants.py
tsf/forecaster.py
tsf/helper.py
tsf/timeseries_modeling.py
tsf/timeseries_reverse_transformations.py
tsf/timeseries_stat_test.py
tsf/timeseries_transformations.py
tsf-0.1.7.dist-info/METADATA
tsf-0.1.7.dist-info/WHEEL
tsf-0.1.7.dist-info/entry_points.txt
tsf-0.1.7.dist-info/top_level.txt
tsf-0.1.7.dist-info/RECORD
