Metadata-Version: 2.1
Name: tsf
Version: 0.1.7
Summary: A library to forecast timeseires data
Home-page: UNKNOWN
Author: Tanushree Halder, Pronojit Saha
Author-email: tanushree.halder@abzooba.com, pronojit.saha@abzooba.com
License: MIT
Platform: UNKNOWN
Classifier: License :: OSI Approved :: MIT License
Classifier: Programming Language :: Python :: 3.7
Requires-Dist: cython (==0.29.14)
Requires-Dist: numpy (>=1.16)
Requires-Dist: pandas
Requires-Dist: arch
Requires-Dist: statsmodels
Requires-Dist: pmdarima
